<flv_mdata><keyframes><times>0, 12, 24, 36, 48, 60, 72, 84, 96, 108, 120, 129.533, 139.066, 151.066, 163.066, 175.066, 184.066, 193.1, 193.766, 205.766, 217.766, 229.766, 241.766, 253.766, 265.766, 277.766, 289.766, 301.766, 313.766, 325.766, 337.766, 349.766, 361.766, 373.766, 385.766, 397.766, 409.766, 421.766, 433.766, 445.766, 454.133, 462.433</times><filepositions>378, 575143, 1098401, 1692590, 2300299, 2904193, 3422332, 3935008, 4410649, 4761726, 5102326, 5533739, 5924182, 6328418, 6822498, 7299516, 7598329, 7888998, 7927130, 8540466, 9067637, 9580961, 9987056, 10504366, 11003911, 11621469, 12240997, 12866038, 13449705, 14012869, 14684900, 15235670, 15773029, 16429914, 17038371, 17596901, 18129610, 18677805, 19147574, 19629853, 19932992, 20171244</filepositions></keyframes><video_width>320</video_width><video_height>240</video_height></flv_mdata>